seatools/__init__.py
seatools/base.py
seatools/env.py
seatools/algorithm/__init__.py
seatools/algorithm/similarity.py
seatools/builders/__init__.py
seatools/builders/base.py
seatools/builders/html.py
seatools/builders/markdown.py
seatools/cache/__init__.py
seatools/cache/cache.py
seatools/cache/ext/__init__.py
seatools/cache/ext/sqlite.py
seatools/clickhouse/__init__.py
seatools/clickhouse/clickhouse_driver.py
seatools/cryptography/__init__.py
seatools/cryptography/aes.py
seatools/cryptography/base.py
seatools/cryptography/base64.py
seatools/cryptography/hmac.py
seatools/cryptography/md5.py
seatools/exceptions/__init__.py
seatools/exceptions/base.py
seatools/fastapi/__init__.py
seatools/fastapi/base.py
seatools/files/__init__.py
seatools/files/base.py
seatools/files/csv.py
seatools/files/eval.py
seatools/files/excel.py
seatools/files/ini.py
seatools/files/json.py
seatools/files/properties.py
seatools/files/py.py
seatools/files/xml.py
seatools/files/yaml.py
seatools/func/__init__.py
seatools/func/ease.py
seatools/id/__init__.py
seatools/id/snowflake.py
seatools/impala/__init__.py
seatools/impala/impyla.py
seatools/ioc/__init__.py
seatools/ioc/base.py
seatools/ioc/constants.py
seatools/ioc/context.py
seatools/ioc/aop/__init__.py
seatools/ioc/aop/aspect.py
seatools/ioc/aop/matcher.py
seatools/ioc/aop/point.py
seatools/ioc/aop/selector.py
seatools/ioc/beans/__init__.py
seatools/ioc/beans/factory/__init__.py
seatools/ioc/beans/factory/base.py
seatools/ioc/beans/factory/initializing_bean.py
seatools/ioc/beans/factory/simple.py
seatools/ioc/beans/proxy/__init__.py
seatools/ioc/beans/proxy/base.py
seatools/ioc/beans/proxy/delay.py
seatools/ioc/boot/__init__.py
seatools/ioc/boot/base.py
seatools/ioc/config/__init__.py
seatools/ioc/config/config.py
seatools/ioc/database/__init__.py
seatools/ioc/database/dbconfig.py
seatools/ioc/environment/__init__.py
seatools/ioc/environment/enviroment.py
seatools/ioc/fastapi/__init__.py
seatools/ioc/fastapi/adapter.py
seatools-1.0.45.dist-info/licenses/LICENSE
seatools-1.0.45.dist-info/METADATA
seatools-1.0.45.dist-info/WHEEL
seatools-1.0.45.dist-info/top_level.txt
seatools-1.0.45.dist-info/RECORD
