Metadata-Version: 2.4
Name: seatools
Version: 1.0.45
Summary: python集成工具包
Home-page: https://gitee.com/dragons96/seatools
Author: dragons96
Author-email: 521274311@qq.com
License: MIT license
Keywords: seatools
Classifier: Development Status :: 2 - Pre-Alpha
Classifier: Intended Audience :: Developers
Classifier: License :: OSI Approved :: MIT License
Classifier: Natural Language :: English
Classifier: Programming Language :: Python :: 3.9
Requires-Python: >=3.9
License-File: LICENSE
Requires-Dist: pydantic>=2.6.0
Requires-Dist: pyyaml>=6.0.0
Requires-Dist: requests>=2.31.0
Requires-Dist: loguru>=0.7.0
Requires-Dist: pycryptodome>=3.20.0
Requires-Dist: xmltodict>=0.13.0
Requires-Dist: contextvars
Provides-Extra: mysql
Requires-Dist: pymysql>=1.1.0; extra == "mysql"
Provides-Extra: orm
Requires-Dist: sqlalchemy>=2.0.27; extra == "orm"
Provides-Extra: impala
Requires-Dist: impyla>=0.19.0; extra == "impala"
Provides-Extra: clickhouse
Requires-Dist: clickhouse-driver>=0.2.7; extra == "clickhouse"
Provides-Extra: orm-clickhouse
Requires-Dist: sqlalchemy>=2.0.27; extra == "orm-clickhouse"
Requires-Dist: clickhouse-sqlalchemy; extra == "orm-clickhouse"
Provides-Extra: hive
Requires-Dist: pyhive; extra == "hive"
Requires-Dist: thrift; extra == "hive"
Requires-Dist: thrift-sasl; extra == "hive"
Provides-Extra: fastapi
Requires-Dist: fastapi>=0.110.0; extra == "fastapi"
Requires-Dist: uvicorn[standard]>=0.29.0; extra == "fastapi"
Provides-Extra: aes
Requires-Dist: pycryptodome>=3.20.0; extra == "aes"
Provides-Extra: all
Requires-Dist: pymysql>=1.1.0; extra == "all"
Requires-Dist: sqlalchemy>=2.0.27; extra == "all"
Requires-Dist: impyla>=0.19.0; extra == "all"
Requires-Dist: clickhouse-driver>=0.2.7; extra == "all"
Requires-Dist: fastapi>=0.110.0; extra == "all"
Requires-Dist: uvicorn[standard]>=0.29.0; extra == "all"
Requires-Dist: pycryptodome>=3.20.0; extra == "all"
Requires-Dist: pyhive; extra == "all"
Requires-Dist: thrift; extra == "all"
Requires-Dist: thrift-sasl; extra == "all"
Requires-Dist: pycryptodome>=3.20.0; extra == "all"
Dynamic: author
Dynamic: author-email
Dynamic: classifier
Dynamic: home-page
Dynamic: keywords
Dynamic: license
Dynamic: license-file
Dynamic: provides-extra
Dynamic: requires-dist
Dynamic: requires-python
Dynamic: summary
